generator.py
Digo_generator-0.0.2.dist-info/LICENSE
Digo_generator-0.0.2.dist-info/METADATA
Digo_generator-0.0.2.dist-info/WHEEL
Digo_generator-0.0.2.dist-info/top_level.txt
Digo_generator-0.0.2.dist-info/RECORD
